{
  "updated": "2026年07月23日 14:39",
  "updatedAtMs": 1784785189622,
  "fetched": 163,
  "universeTotal": 166,
  "market": {
    "regime": "bull",
    "label": "上昇基調",
    "desc": "市場全体（TOPIX）は200日移動平均の上で推移しており、比較的良好な地合いです。",
    "priceVsMa200Pct": 13.5,
    "source": "TOPIX連動ETF(1306.T)終値と200日移動平均から判定"
  },
  "marketOutlook": {
    "spxChangePct": -0.14,
    "spxDate": "2026-07-22",
    "usdjpy": 163.07,
    "usdjpyChangePct": -0.07,
    "condition": "米S&P500が直近下落",
    "topixUpRate": 43.0,
    "n": 207,
    "regime": "bull",
    "basis": "過去2年で「米国市場が上昇/下落した翌営業日に東京(TOPIX ETF)が上昇した割合」を実際に集計。統計的傾向であり将来を保証しません。出典: Yahoo Finance価格データ。"
  },
  "accuracy": {
    "resolvedStockCount": 101,
    "resolvedMarketCount": 9,
    "rangeHitRate": 84.2,
    "leanUpActualUp": 50.0,
    "leanUpN": 18,
    "leanDownActualUp": 66.7,
    "leanDownN": 6,
    "marketHitRate": 44.4,
    "planEntered": 42,
    "planDecided": 42,
    "planTargetRate": 45.2,
    "planExpired": 0,
    "sinceDate": "2026-07-06",
    "note": "予測と実際の答え合わせを毎営業日ぶん蓄積した実績です。件数が増えるほど信頼度が上がります。将来を保証するものではありません。"
  },
  "backtest": {
    "annual": "+29.9%",
    "benchmark": "+30.4%",
    "sharpe": "0.86",
    "dd": "-16.9%",
    "winrate": "60.9%",
    "months": "23ヶ月",
    "note": "検証方法: 前月末までの6ヶ月騰落率上位10銘柄を翌月保有・月次入替（先読みなし・手数料0.1%/月控除）。同期間のTOPIX連動ETF(1306)は年率+30.4%。これは総合スコアのうち勢い(モメンタム)成分のみの近似検証で、割安度・稼ぐ力を含む総合スコア自体の検証ではありません。過去の実績であり、将来の成果を保証するものではありません。"
  },
  "stocks": [
    {
      "rank": 1,
      "ticker": "7201.T",
      "name": "日産自動車",
      "score": 0.624,
      "f": 2,
      "per": null,
      "pbr": 0.24,
      "roe": -9.9,
      "value": 1.0,
      "quality": 0.355,
      "momentum": 0.168,
      "smart": 0.871,
      "smartMoney": {
        "score": 0.563,
        "label": "買い集めの兆候",
        "tone": "pos",
        "cmf": 0.058,
        "mfi": 73.1,
        "obvSlope": 0.44,
        "vwapDevPct": 5.6,
        "factors": [
          "上昇日に出来高が集中（OBV上向き）",
          "直近平均コスト(VWAP)を上回って推移",
          "直近5日は買い方向の出来高が優勢"
        ]
      },
      "smartAdjusted": null,
      "signal": "買い",
      "rsi": 63.4,
      "conf": "中",
      "strategy": [
        "low_price"
      ],
      "dividend_yield": 0.0,
      "volatility": 0.4268,
      "short_ratio": 2.93,
      "regime_adjusted": false,
      "forecast": {
        "price": 331.0,
        "rangeLow": 323,
        "rangeHigh": 339,
        "rangeLow2": 314,
        "rangeHigh2": 348,
        "volDPct": 2.53,
        "calibrated": true,
        "plan": {
          "entry": 327,
          "target": 344,
          "stop": 314,
          "rr": 1.31,
          "hi3m": 399,
          "lo3m": 300,
          "basis": "1日の実績振れ幅σ=2.5%を単位に、買い目安=現値-0.5σ・利確=買値+2σ・損切り=買値-1.5σで機械的に算出（利益:損失の比率 1.3:1）。参考: 直近3ヶ月の高値399円 / 安値300円。この目安が実際に機能したかは毎営業日答え合わせして下の実績に反映します。損切りは必ずセットで守ることを想定した設計です。"
        },
        "cond": {
          "upRate": 45.6,
          "n": 193,
          "condition": "RSI中立圏×5日上昇局面",
          "note": null
        },
        "factors": [
          {
            "label": "空売り残高2.93%（売り圧力・踏み上げ両方の要因）",
            "dir": "-"
          }
        ],
        "basis": "レンジは過去2年の日次値動きの標準偏差を、答え合わせ実績で当たり幅に合わせて補正したもの。実績確率は同条件だった過去の日の翌日騰落を実際に集計。統計的傾向であり将来を保証しません。（答え合わせ実績に基づきレンジ幅を0.82倍に自動補正済み。目標カバー率は約75%）"
      },
      "yutai": null,
      "news": [
        {
          "title": "日産自動車、2025年度第3四半期決算を発表し、通期業績見通しを修正",
          "source": "日産自動車ニュースルーム",
          "url": "https://news.google.com/rss/articles/CBMiZ0FVX3lxTE5TOElqOHk3VG9RbGJDcE1KZE1JTDlyeS1XNEZEbGYyTWROblNOaTFzS19WRzZzT3dBRTVOYnhrQW9kRzB2b0NpQllocmk2ZnozcGpnOGthSm0zOGpOZXA0WWM3RThLTjg?oc=5",
          "pubDate": "Thu, 12 Feb 2026 08:00:00 GMT",
          "sentiment": "neu",
          "theme": "自動車"
        }
      ]
    },
    {
      "rank": 2,
      "ticker": "9501.T",
      "name": "東京電力HD",
      "score": 0.598,
      "f": 2,
      "per": null,
      "pbr": 0.24,
      "roe": -12.6,
      "value": 0.989,
      "quality": 0.328,
      "momentum": 0.132,
      "smart": 0.863,
      "smartMoney": {
        "score": 0.55,
        "label": "買い集めの兆候",
        "tone": "pos",
        "cmf": 0.112,
        "mfi": 73.3,
        "obvSlope": 0.28,
        "vwapDevPct": 7.1,
        "factors": [
          "安値圏でも買われている（CMFプラス）",
          "上昇日に出来高が集中（OBV上向き）",
          "直近平均コスト(VWAP)を上回って推移",
          "直近5日は買い方向の出来高が優勢"
        ]
      },
      "smartAdjusted": null,
      "signal": "売り",
      "rsi": 81.2,
      "conf": "中",
      "strategy": [
        "swing"
      ],
      "dividend_yield": 0.0,
      "volatility": 0.5394,
      "short_ratio": 0.95,
      "regime_adjusted": false,
      "forecast": {
        "price": 515.9,
        "rangeLow": 502,
        "rangeHigh": 529,
        "rangeLow2": 489,
        "rangeHigh2": 543,
        "volDPct": 2.6,
        "calibrated": true,
        "plan": {
          "entry": 509,
          "target": 536,
          "stop": 489,
          "rr": 1.35,
          "hi3m": 651,
          "lo3m": 455,
          "basis": "1日の実績振れ幅σ=2.6%を単位に、買い目安=現値-0.5σ・利確=買値+2σ・損切り=買値-1.5σで機械的に算出（利益:損失の比率 1.4:1）。参考: 直近3ヶ月の高値651円 / 安値455円。この目安が実際に機能したかは毎営業日答え合わせして下の実績に反映します。損切りは必ずセットで守ることを想定した設計です。"
        },
        "cond": {
          "upRate": 53.3,
          "n": 45,
          "condition": "RSI70以上（買われすぎ圏）×5日上昇局面",
          "note": null
        },
        "factors": [
          {
            "label": "RSI 81.2（買われすぎ圏・反落しやすい傾向）",
            "dir": "-"
          }
        ],
        "basis": "レンジは過去2年の日次値動きの標準偏差を、答え合わせ実績で当たり幅に合わせて補正したもの。実績確率は同条件だった過去の日の翌日騰落を実際に集計。統計的傾向であり将来を保証しません。（答え合わせ実績に基づきレンジ幅を0.82倍に自動補正済み。目標カバー率は約75%）"
      },
      "yutai": null,
      "news": [
        {
          "title": "東京電力(株)【9501】：今の株価の理由は？値動きの背景をAIが解説",
          "source": "Yahoo!ファイナンス",
          "url": "https://news.google.com/rss/articles/CBMiX0FVX3lxTE1FLU53MFRkZVpONnFvcmJJTkF5anN6OURqdEtYd1NTMXBxOVBTUEJ6UFZ2Y0Y4ODR5RE94OEM3b0RuXzFPWkVmWXVQVVNIWEdkNzFnNlZSZzczd1Jvd2xj?oc=5",
          "pubDate": "Tue, 21 Jul 2026 06:53:40 GMT",
          "sentiment": "neu",
          "theme": "AI"
        }
      ]
    },
    {
      "rank": 3,
      "ticker": "5401.T",
      "name": "日本製鉄",
      "score": 0.59,
      "f": 4,
      "per": 185.2,
      "pbr": 0.58,
      "roe": 0.8,
      "value": 0.423,
      "quality": 0.456,
      "momentum": 0.214,
      "smart": 1.0,
      "smartMoney": {
        "score": 0.765,
        "label": "買い集めの兆候",
        "tone": "pos",
        "cmf": 0.174,
        "mfi": 84.3,
        "obvSlope": 0.42,
        "vwapDevPct": 8.1,
        "factors": [
          "安値圏でも買われている（CMFプラス）",
          "上昇日に出来高が集中（OBV上向き）",
          "直近平均コスト(VWAP)を上回って推移",
          "直近5日は買い方向の出来高が優勢"
        ]
      },
      "smartAdjusted": null,
      "signal": "売り",
      "rsi": 88.5,
      "conf": "中",
      "strategy": [
        "dividend"
      ],
      "dividend_yield": 4.0,
      "volatility": 0.2669,
      "short_ratio": null,
      "regime_adjusted": false,
      "forecast": {
        "price": 609.4,
        "rangeLow": 601,
        "rangeHigh": 618,
        "rangeLow2": 593,
        "rangeHigh2": 626,
        "volDPct": 1.36,
        "calibrated": true,
        "plan": {
          "entry": 605,
          "target": 622,
          "stop": 593,
          "rr": 1.42,
          "hi3m": 609,
          "lo3m": 531,
          "basis": "1日の実績振れ幅σ=1.4%を単位に、買い目安=現値-0.5σ・利確=買値+2σ・損切り=買値-1.5σで機械的に算出（利益:損失の比率 1.4:1）。参考: 直近3ヶ月の高値609円 / 安値531円。この目安が実際に機能したかは毎営業日答え合わせして下の実績に反映します。損切りは必ずセットで守ることを想定した設計です。"
        },
        "cond": {
          "upRate": 54.9,
          "n": 51,
          "condition": "RSI70以上（買われすぎ圏）×5日上昇局面",
          "note": null
        },
        "factors": [
          {
            "label": "RSI 88.5（買われすぎ圏・反落しやすい傾向）",
            "dir": "-"
          }
        ],
        "basis": "レンジは過去2年の日次値動きの標準偏差を、答え合わせ実績で当たり幅に合わせて補正したもの。実績確率は同条件だった過去の日の翌日騰落を実際に集計。統計的傾向であり将来を保証しません。（答え合わせ実績に基づきレンジ幅を0.82倍に自動補正済み。目標カバー率は約75%）"
      },
      "yutai": null,
      "news": [
        {
          "title": "日本製鉄(株)【5401】：今の株価の理由は？値動きの背景をAIが解説",
          "source": "Yahoo!ファイナンス",
          "url": "https://news.google.com/rss/articles/CBMiX0FVX3lxTFBacjZQcWtoaGdTaTZ3M1BOYldUdU5zWnhHb3pYVWVxcDNTQndrdHRndVYyZ0QzTnIwdEpoWFZIeXlHZDAwenNFWEJrZldFUF96b1VaN3VQc2lGeXZBdEVV?oc=5",
          "pubDate": "Wed, 22 Jul 2026 06:53:20 GMT",
          "sentiment": "neu",
          "theme": "AI"
        }
      ]
    },
    {
      "rank": 4,
      "ticker": "6178.T",
      "name": "日本郵政",
      "score": 0.582,
      "f": 6,
      "per": 19.1,
      "pbr": 0.71,
      "roe": 4.7,
      "value": 0.355,
      "quality": 0.494,
      "momentum": 0.416,
      "smart": 0.847,
      "smartMoney": {
        "score": 0.525,
        "label": "買い集めの兆候",
        "tone": "pos",
        "cmf": 0.153,
        "mfi": 69.5,
        "obvSlope": 0.17,
        "vwapDevPct": 6.7,
        "factors": [
          "安値圏でも買われている（CMFプラス）",
          "直近平均コスト(VWAP)を上回って推移"
        ]
      },
      "smartAdjusted": null,
      "signal": "様子見",
      "rsi": 73.4,
      "conf": "低",
      "strategy": [
        "swing"
      ],
      "dividend_yield": 2.5,
      "volatility": 0.3147,
      "short_ratio": null,
      "regime_adjusted": false,
      "forecast": {
        "price": 2464.0,
        "rangeLow": 2422,
        "rangeHigh": 2506,
        "rangeLow2": 2381,
        "rangeHigh2": 2547,
        "volDPct": 1.69,
        "calibrated": true,
        "plan": {
          "entry": 2443,
          "target": 2526,
          "stop": 2381,
          "rr": 1.34,
          "hi3m": 2464,
          "lo3m": 1758,
          "basis": "1日の実績振れ幅σ=1.7%を単位に、買い目安=現値-0.5σ・利確=買値+2σ・損切り=買値-1.5σで機械的に算出（利益:損失の比率 1.3:1）。参考: 直近3ヶ月の高値2,464円 / 安値1,758円。この目安が実際に機能したかは毎営業日答え合わせして下の実績に反映します。損切りは必ずセットで守ることを想定した設計です。"
        },
        "cond": {
          "upRate": 44.3,
          "n": 70,
          "condition": "RSI70以上（買われすぎ圏）×5日上昇局面",
          "note": null
        },
        "factors": [
          {
            "label": "RSI 73.4（買われすぎ圏・反落しやすい傾向）",
            "dir": "-"
          }
        ],
        "basis": "レンジは過去2年の日次値動きの標準偏差を、答え合わせ実績で当たり幅に合わせて補正したもの。実績確率は同条件だった過去の日の翌日騰落を実際に集計。統計的傾向であり将来を保証しません。（答え合わせ実績に基づきレンジ幅を0.82倍に自動補正済み。目標カバー率は約75%）"
      },
      "yutai": null,
      "news": [
        {
          "title": "郵便局網の維持に「国費」投入へ 金融２社株は当面保有、改正法",
          "source": "山陽新聞",
          "url": "https://news.google.com/rss/articles/CBMie0FVX3lxTE1DN09PZ05FLUYyVDJNUXBXdjVxSUVjeWNrNVFaY0xqbDdzX0hUQ3hGUXlwVFhvbUFhZ3BjMWQ4VjRueGI5ZnFnUVV0SlQ3UUVFT3VmNUFCNllfTHBhM0xQcUl0T0ZxYlMydzlBa1hJYjlNZVplbzFISmhQbw?oc=5",
          "pubDate": "Wed, 22 Jul 2026 15:17:54 GMT",
          "sentiment": "neu",
          "theme": "その他"
        }
      ]
    },
    {
      "rank": 5,
      "ticker": "9101.T",
      "name": "日本郵船",
      "score": 0.579,
      "f": 6,
      "per": 11.5,
      "pbr": 0.76,
      "roe": 7.1,
      "value": 0.341,
      "quality": 0.516,
      "momentum": 0.329,
      "smart": 0.902,
      "smartMoney": {
        "score": 0.612,
        "label": "買い集めの兆候",
        "tone": "pos",
        "cmf": 0.136,
        "mfi": 76.3,
        "obvSlope": 0.21,
        "vwapDevPct": 7.1,
        "factors": [
          "安値圏でも買われている（CMFプラス）",
          "上昇日に出来高が集中（OBV上向き）",
          "直近平均コスト(VWAP)を上回って推移",
          "直近5日は買い方向の出来高が優勢"
        ]
      },
      "smartAdjusted": null,
      "signal": "様子見",
      "rsi": 72.8,
      "conf": "低",
      "strategy": [
        "dividend"
      ],
      "dividend_yield": 3.4,
      "volatility": 0.296,
      "short_ratio": 1.06,
      "regime_adjusted": false,
      "forecast": {
        "price": 5785.0,
        "rangeLow": 5692,
        "rangeHigh": 5878,
        "rangeLow2": 5599,
        "rangeHigh2": 5971,
        "volDPct": 1.61,
        "calibrated": true,
        "plan": {
          "entry": 5738,
          "target": 5924,
          "stop": 5598,
          "rr": 1.33,
          "hi3m": 5874,
          "lo3m": 5080,
          "basis": "1日の実績振れ幅σ=1.6%を単位に、買い目安=現値-0.5σ・利確=買値+2σ・損切り=買値-1.5σで機械的に算出（利益:損失の比率 1.3:1）。参考: 直近3ヶ月の高値5,874円 / 安値5,080円。この目安が実際に機能したかは毎営業日答え合わせして下の実績に反映します。損切りは必ずセットで守ることを想定した設計です。"
        },
        "cond": {
          "upRate": 54.7,
          "n": 64,
          "condition": "RSI70以上（買われすぎ圏）×5日上昇局面",
          "note": null
        },
        "factors": [
          {
            "label": "RSI 72.8（買われすぎ圏・反落しやすい傾向）",
            "dir": "-"
          }
        ],
        "basis": "レンジは過去2年の日次値動きの標準偏差を、答え合わせ実績で当たり幅に合わせて補正したもの。実績確率は同条件だった過去の日の翌日騰落を実際に集計。統計的傾向であり将来を保証しません。（答え合わせ実績に基づきレンジ幅を0.82倍に自動補正済み。目標カバー率は約75%）"
      },
      "yutai": "なし（日本郵船は株主優待制度なし）",
      "news": [
        {
          "title": "日本郵船(株)【NPNYY】：株価・株式情報",
          "source": "Yahoo!ファイナンス",
          "url": "https://news.google.com/rss/articles/CBMiUEFVX3lxTFBSeFBNOW5HUmFRa3BGa1NsYmZzTnNNZm1wZGxtNVJkQTVWZS1PY0w1OHV5UF90VC0wTTlBZkNsdWVsdzhTV21PWGxMcl9PWEtp?oc=5",
          "pubDate": "Thu, 23 Jul 2026 00:11:09 GMT",
          "sentiment": "neu",
          "theme": "その他"
        }
      ]
    },
    {
      "rank": 6,
      "ticker": "7751.T",
      "name": "キヤノン",
      "score": 0.571,
      "f": 6,
      "per": 12.3,
      "pbr": 1.14,
      "roe": 9.4,
      "value": 0.235,
      "quality": 0.539,
      "momentum": 0.244,
      "smart": 0.98,
      "smartMoney": {
        "score": 0.734,
        "label": "買い集めの兆候",
        "tone": "pos",
        "cmf": 0.203,
        "mfi": 80.2,
        "obvSlope": 0.28,
        "vwapDevPct": 5.0,
        "factors": [
          "安値圏でも買われている（CMFプラス）",
          "上昇日に出来高が集中（OBV上向き）",
          "直近平均コスト(VWAP)を上回って推移",
          "直近5日は買い方向の出来高が優勢"
        ]
      },
      "smartAdjusted": null,
      "signal": "売り",
      "rsi": 78.5,
      "conf": "中",
      "strategy": [
        "dividend"
      ],
      "dividend_yield": 3.5,
      "volatility": 0.2249,
      "short_ratio": 0.71,
      "regime_adjusted": false,
      "forecast": {
        "price": 4517.0,
        "rangeLow": 4452,
        "rangeHigh": 4582,
        "rangeLow2": 4387,
        "rangeHigh2": 4647,
        "volDPct": 1.43,
        "calibrated": true,
        "plan": {
          "entry": 4485,
          "target": 4615,
          "stop": 4388,
          "rr": 1.34,
          "hi3m": 4536,
          "lo3m": 3930,
          "basis": "1日の実績振れ幅σ=1.4%を単位に、買い目安=現値-0.5σ・利確=買値+2σ・損切り=買値-1.5σで機械的に算出（利益:損失の比率 1.3:1）。参考: 直近3ヶ月の高値4,536円 / 安値3,930円。この目安が実際に機能したかは毎営業日答え合わせして下の実績に反映します。損切りは必ずセットで守ることを想定した設計です。"
        },
        "cond": {
          "upRate": 50.0,
          "n": 32,
          "condition": "RSI70以上（買われすぎ圏）×5日上昇局面",
          "note": null
        },
        "factors": [
          {
            "label": "RSI 78.5（買われすぎ圏・反落しやすい傾向）",
            "dir": "-"
          }
        ],
        "basis": "レンジは過去2年の日次値動きの標準偏差を、答え合わせ実績で当たり幅に合わせて補正したもの。実績確率は同条件だった過去の日の翌日騰落を実際に集計。統計的傾向であり将来を保証しません。（答え合わせ実績に基づきレンジ幅を0.82倍に自動補正済み。目標カバー率は約75%）"
      },
      "yutai": null,
      "news": [
        {
          "title": "キヤノン(株)【7751】：今の株価の理由は？値動きの背景をAIが解説",
          "source": "Yahoo!ファイナンス",
          "url": "https://news.google.com/rss/articles/CBMiX0FVX3lxTFBhLWNZUWFNTDhjR0NVdmV2NUtRZlRzODZrRDFoOFZyN0pjT25LbEJ2UVRBVUN1c2ZSbE1TZGJMSS0tTEl0QWNUN3FzeDlzcGZ3WjlHaW92eDY1bTdhdFgw?oc=5",
          "pubDate": "Tue, 21 Jul 2026 06:57:17 GMT",
          "sentiment": "neu",
          "theme": "AI"
        }
      ]
    },
    {
      "rank": 7,
      "ticker": "5411.T",
      "name": "JFEホールディングス",
      "score": 0.571,
      "f": 5,
      "per": 16.4,
      "pbr": 0.42,
      "roe": 2.8,
      "value": 0.59,
      "quality": 0.476,
      "momentum": 0.168,
      "smart": 0.855,
      "smartMoney": {
        "score": 0.537,
        "label": "買い集めの兆候",
        "tone": "pos",
        "cmf": 0.135,
        "mfi": 67.8,
        "obvSlope": 0.35,
        "vwapDevPct": 6.4,
        "factors": [
          "安値圏でも買われている（CMFプラス）",
          "上昇日に出来高が集中（OBV上向き）",
          "直近平均コスト(VWAP)を上回って推移"
        ]
      },
      "smartAdjusted": null,
      "signal": "売り",
      "rsi": 79.0,
      "conf": "中",
      "strategy": [
        "dividend"
      ],
      "dividend_yield": 4.7,
      "volatility": 0.2726,
      "short_ratio": 4.74,
      "regime_adjusted": false,
      "forecast": {
        "price": 1733.0,
        "rangeLow": 1710,
        "rangeHigh": 1756,
        "rangeLow2": 1687,
        "rangeHigh2": 1779,
        "volDPct": 1.34,
        "calibrated": true,
        "plan": {
          "entry": 1721,
          "target": 1767,
          "stop": 1686,
          "rr": 1.31,
          "hi3m": 1765,
          "lo3m": 1546,
          "basis": "1日の実績振れ幅σ=1.3%を単位に、買い目安=現値-0.5σ・利確=買値+2σ・損切り=買値-1.5σで機械的に算出（利益:損失の比率 1.3:1）。参考: 直近3ヶ月の高値1,765円 / 安値1,546円。この目安が実際に機能したかは毎営業日答え合わせして下の実績に反映します。損切りは必ずセットで守ることを想定した設計です。"
        },
        "cond": {
          "upRate": 52.5,
          "n": 59,
          "condition": "RSI70以上（買われすぎ圏）×5日上昇局面",
          "note": null
        },
        "factors": [
          {
            "label": "RSI 79.0（買われすぎ圏・反落しやすい傾向）",
            "dir": "-"
          },
          {
            "label": "空売り残高4.74%（売り圧力・踏み上げ両方の要因）",
            "dir": "-"
          }
        ],
        "basis": "レンジは過去2年の日次値動きの標準偏差を、答え合わせ実績で当たり幅に合わせて補正したもの。実績確率は同条件だった過去の日の翌日騰落を実際に集計。統計的傾向であり将来を保証しません。（答え合わせ実績に基づきレンジ幅を0.82倍に自動補正済み。目標カバー率は約75%）"
      },
      "yutai": null,
      "news": [
        {
          "title": "ＪＦＥホールディングス(株)【5411】：株つぶやき",
          "source": "Yahoo!ファイナンス",
          "url": "https://news.google.com/rss/articles/CBMiWEFVX3lxTE1CZldMSTEzSzFOUEl4RGVqWXFickFjT05OOFJ4UnhkYV9uNUhtaFFBVGU3Z1pHUmtxa2pjS2NVS0RUUUh5dm1ZaFZEeWlfZHR4bmRndE9yMWQ?oc=5",
          "pubDate": "Tue, 21 Jul 2026 14:29:55 GMT",
          "sentiment": "neu",
          "theme": "その他"
        }
      ]
    },
    {
      "rank": 8,
      "ticker": "9107.T",
      "name": "川崎汽船",
      "score": 0.568,
      "f": 6,
      "per": 13.2,
      "pbr": 0.97,
      "roe": 7.8,
      "value": 0.27,
      "quality": 0.523,
      "momentum": 0.379,
      "smart": 0.886,
      "smartMoney": {
        "score": 0.586,
        "label": "買い集めの兆候",
        "tone": "pos",
        "cmf": 0.114,
        "mfi": 65.4,
        "obvSlope": 0.29,
        "vwapDevPct": 8.5,
        "factors": [
          "安値圏でも買われている（CMFプラス）",
          "上昇日に出来高が集中（OBV上向き）",
          "直近平均コスト(VWAP)を上回って推移",
          "直近5日は買い方向の出来高が優勢"
        ]
      },
      "smartAdjusted": null,
      "signal": "様子見",
      "rsi": 72.2,
      "conf": "低",
      "strategy": [
        "dividend"
      ],
      "dividend_yield": 4.3,
      "volatility": 0.3524,
      "short_ratio": 2.93,
      "regime_adjusted": false,
      "forecast": {
        "price": 2779.0,
        "rangeLow": 2724,
        "rangeHigh": 2834,
        "rangeLow2": 2670,
        "rangeHigh2": 2888,
        "volDPct": 1.97,
        "calibrated": true,
        "plan": {
          "entry": 2752,
          "target": 2861,
          "stop": 2670,
          "rr": 1.33,
          "hi3m": 2779,
          "lo3m": 2418,
          "basis": "1日の実績振れ幅σ=2.0%を単位に、買い目安=現値-0.5σ・利確=買値+2σ・損切り=買値-1.5σで機械的に算出（利益:損失の比率 1.3:1）。参考: 直近3ヶ月の高値2,779円 / 安値2,418円。この目安が実際に機能したかは毎営業日答え合わせして下の実績に反映します。損切りは必ずセットで守ることを想定した設計です。"
        },
        "cond": {
          "upRate": 51.4,
          "n": 74,
          "condition": "RSI70以上（買われすぎ圏）×5日上昇局面",
          "note": null
        },
        "factors": [
          {
            "label": "RSI 72.2（買われすぎ圏・反落しやすい傾向）",
            "dir": "-"
          },
          {
            "label": "空売り残高2.93%（売り圧力・踏み上げ両方の要因）",
            "dir": "-"
          }
        ],
        "basis": "レンジは過去2年の日次値動きの標準偏差を、答え合わせ実績で当たり幅に合わせて補正したもの。実績確率は同条件だった過去の日の翌日騰落を実際に集計。統計的傾向であり将来を保証しません。（答え合わせ実績に基づきレンジ幅を0.82倍に自動補正済み。目標カバー率は約75%）"
      },
      "yutai": null,
      "news": [
        {
          "title": "川崎汽船(株)【9107】：現物信用売買内訳時系列",
          "source": "Yahoo!ファイナンス",
          "url": "https://news.google.com/rss/articles/CBMiX0FVX3lxTE5sTlVlZThLQWViU3pjVnNfckdBVmlCZEFreHR0VTBfMU1tWWVfQ2ZBZ3hHWGJOREo4c2tIMkthOGlzRVpzcnVPNThaRkRYR3hxdGNrTEZkQ0tvekdEa2x3?oc=5",
          "pubDate": "Fri, 17 Jul 2026 07:00:00 GMT",
          "sentiment": "neu",
          "theme": "その他"
        }
      ]
    },
    {
      "rank": 9,
      "ticker": "8306.T",
      "name": "三菱UFJ",
      "score": 0.563,
      "f": 7,
      "per": 17.7,
      "pbr": 2.17,
      "roe": 9.4,
      "value": 0.13,
      "quality": 0.539,
      "momentum": 0.411,
      "smart": 0.925,
      "smartMoney": {
        "score": 0.647,
        "label": "買い集めの兆候",
        "tone": "pos",
        "cmf": 0.185,
        "mfi": 72.7,
        "obvSlope": 0.42,
        "vwapDevPct": 8.6,
        "factors": [
          "安値圏でも買われている（CMFプラス）",
          "上昇日に出来高が集中（OBV上向き）",
          "直近平均コスト(VWAP)を上回って推移"
        ]
      },
      "smartAdjusted": null,
      "signal": "様子見",
      "rsi": 73.7,
      "conf": "低",
      "strategy": [
        "dividend"
      ],
      "dividend_yield": 2.6,
      "volatility": 0.3411,
      "short_ratio": null,
      "regime_adjusted": false,
      "forecast": {
        "price": 3767.0,
        "rangeLow": 3695,
        "rangeHigh": 3839,
        "rangeLow2": 3623,
        "rangeHigh2": 3911,
        "volDPct": 1.91,
        "calibrated": true,
        "plan": {
          "entry": 3731,
          "target": 3875,
          "stop": 3623,
          "rr": 1.33,
          "hi3m": 3767,
          "lo3m": 2756,
          "basis": "1日の実績振れ幅σ=1.9%を単位に、買い目安=現値-0.5σ・利確=買値+2σ・損切り=買値-1.5σで機械的に算出（利益:損失の比率 1.3:1）。参考: 直近3ヶ月の高値3,767円 / 安値2,756円。この目安が実際に機能したかは毎営業日答え合わせして下の実績に反映します。損切りは必ずセットで守ることを想定した設計です。"
        },
        "cond": {
          "upRate": 47.2,
          "n": 72,
          "condition": "RSI70以上（買われすぎ圏）×5日上昇局面",
          "note": null
        },
        "factors": [
          {
            "label": "RSI 73.7（買われすぎ圏・反落しやすい傾向）",
            "dir": "-"
          }
        ],
        "basis": "レンジは過去2年の日次値動きの標準偏差を、答え合わせ実績で当たり幅に合わせて補正したもの。実績確率は同条件だった過去の日の翌日騰落を実際に集計。統計的傾向であり将来を保証しません。（答え合わせ実績に基づきレンジ幅を0.82倍に自動補正済み。目標カバー率は約75%）"
      },
      "yutai": null,
      "news": [
        {
          "title": "純金上場信託(現物国内保管型)【1540】：株価・株式情報（夜間PTS含む）",
          "source": "Yahoo!ファイナンス",
          "url": "https://news.google.com/rss/articles/CBMiUkFVX3lxTE4wT0pLZFYweEZKZEI1MWVnSDNHYXJfemt1T1FNNDFfai1kRkFoVGp2Y0pLemJYVGRIUDc2VGNXVUlUSUFFdTNscnZBME81Ml9Oenc?oc=5",
          "pubDate": "Thu, 23 Jul 2026 01:09:53 GMT",
          "sentiment": "neu",
          "theme": "その他"
        }
      ]
    },
    {
      "rank": 10,
      "ticker": "8725.T",
      "name": "MS&ADインシュアランス",
      "score": 0.563,
      "f": 7,
      "per": 14.2,
      "pbr": 1.1,
      "roe": 9.8,
      "value": 0.241,
      "quality": 0.543,
      "momentum": 0.362,
      "smart": 0.876,
      "smartMoney": {
        "score": 0.57,
        "label": "買い集めの兆候",
        "tone": "pos",
        "cmf": 0.234,
        "mfi": 59.0,
        "obvSlope": 0.06,
        "vwapDevPct": 9.3,
        "factors": [
          "安値圏でも買われている（CMFプラス）",
          "直近平均コスト(VWAP)を上回って推移",
          "直近5日は買い方向の出来高が優勢"
        ]
      },
      "smartAdjusted": null,
      "signal": "売り",
      "rsi": 76.1,
      "conf": "中",
      "strategy": [
        "dividend"
      ],
      "dividend_yield": 2.9,
      "volatility": 0.2933,
      "short_ratio": null,
      "regime_adjusted": false,
      "forecast": {
        "price": 4868.0,
        "rangeLow": 4782,
        "rangeHigh": 4954,
        "rangeLow2": 4695,
        "rangeHigh2": 5041,
        "volDPct": 1.78,
        "calibrated": true,
        "plan": {
          "entry": 4825,
          "target": 4998,
          "stop": 4695,
          "rr": 1.33,
          "hi3m": 4868,
          "lo3m": 3931,
          "basis": "1日の実績振れ幅σ=1.8%を単位に、買い目安=現値-0.5σ・利確=買値+2σ・損切り=買値-1.5σで機械的に算出（利益:損失の比率 1.3:1）。参考: 直近3ヶ月の高値4,868円 / 安値3,931円。この目安が実際に機能したかは毎営業日答え合わせして下の実績に反映します。損切りは必ずセットで守ることを想定した設計です。"
        },
        "cond": {
          "upRate": 51.4,
          "n": 70,
          "condition": "RSI70以上（買われすぎ圏）×5日上昇局面",
          "note": null
        },
        "factors": [
          {
            "label": "RSI 76.1（買われすぎ圏・反落しやすい傾向）",
            "dir": "-"
          }
        ],
        "basis": "レンジは過去2年の日次値動きの標準偏差を、答え合わせ実績で当たり幅に合わせて補正したもの。実績確率は同条件だった過去の日の翌日騰落を実際に集計。統計的傾向であり将来を保証しません。（答え合わせ実績に基づきレンジ幅を0.82倍に自動補正済み。目標カバー率は約75%）"
      },
      "yutai": null,
      "news": [
        {
          "title": "ＭＳ＆ＡＤインシュアランスグループホールディングス(株)【8725】：企業情報（決算時期や平均年収、代表者名など）",
          "source": "Yahoo!ファイナンス",
          "url": "https://news.google.com/rss/articles/CBMiXEFVX3lxTE5WWjY3QVFuZkRtb1BROFBTVHNPelozOElqVHRvb1pxWWE4UEFDQTdJeTRsU2UxWU5YY2UxU0JPX3EtQWs0UmpDNjhkaGdnejRvaDM5TFFZc3p2NUhs?oc=5",
          "pubDate": "Fri, 17 Jul 2026 07:00:00 GMT",
          "sentiment": "neu",
          "theme": "その他"
        }
      ]
    }
  ],
  "stockMaster": [
    {
      "code": "6861.T",
      "name": "キーエンス",
      "price": 72530.0,
      "divPerShare": 550.0,
      "exDivDate": "2026-09-17",
      "dividendYield": 0.76,
      "per": 39.4,
      "pbr": 5.07,
      "roe": 13.5,
      "rsi": 29.7,
      "vol": 0.4701,
      "inTop": false,
      "yutai": null
    },
    {
      "code": "7203.T",
      "name": "トヨタ自動車",
      "price": 2942.0,
      "divPerShare": 100.0,
      "exDivDate": "2026-09-29",
      "dividendYield": 3.4,
      "per": 10.0,
      "pbr": 0.96,
      "roe": 10.2,
      "rsi": 66.2,
      "vol": 0.3213,
      "inTop": false,
      "yutai": "なし（株主優待は廃止）"
    },
    {
      "code": "6758.T",
      "name": "ソニーグループ",
      "price": 3434.0,
      "divPerShare": 35.0,
      "exDivDate": "2026-09-29",
      "dividendYield": 1.02,
      "per": 20.0,
      "pbr": 2.5,
      "roe": 12.3,
      "rsi": 60.4,
      "vol": 0.3641,
      "inTop": false,
      "yutai": null
    },
    {
      "code": "4063.T",
      "name": "信越化学",
      "price": 7017.0,
      "divPerShare": 106.0,
      "exDivDate": "2026-03-30",
      "dividendYield": 1.5,
      "per": 27.8,
      "pbr": 2.92,
      "roe": 10.7,
      "rsi": 49.9,
      "vol": 0.4749,
      "inTop": false,
      "yutai": null
    },
    {
      "code": "6326.T",
      "name": "クボタ",
      "price": 2794.0,
      "divPerShare": 52.0,
      "exDivDate": "2026-12-29",
      "dividendYield": 1.88,
      "per": 17.1,
      "pbr": 1.18,
      "roe": 8.9,
      "rsi": 60.9,
      "vol": 0.4795,
      "inTop": false,
      "yutai": null
    },
    {
      "code": "8035.T",
      "name": "東京エレクトロン",
      "price": 66350.0,
      "divPerShare": 722.0,
      "exDivDate": "2026-09-29",
      "dividendYield": 1.09,
      "per": 53.0,
      "pbr": 14.58,
      "roe": 29.3,
      "rsi": 38.3,
      "vol": 0.6088,
      "inTop": false,
      "yutai": null
    },
    {
      "code": "6501.T",
      "name": "日立製作所",
      "price": 4838.0,
      "divPerShare": 55.0,
      "exDivDate": "2026-09-29",
      "dividendYield": 1.14,
      "per": 27.4,
      "pbr": 3.31,
      "roe": 13.3,
      "rsi": 58.5,
      "vol": 0.4067,
      "inTop": false,
      "yutai": null
    },
    {
      "code": "6902.T",
      "name": "デンソー",
      "price": 1987.0,
      "divPerShare": 74.0,
      "exDivDate": "2026-09-29",
      "dividendYield": 3.72,
      "per": 7.7,
      "pbr": 0.97,
      "roe": 8.9,
      "rsi": 61.7,
      "vol": 0.2648,
      "inTop": false,
      "yutai": null
    },
    {
      "code": "5108.T",
      "name": "ブリヂストン",
      "price": 3739.0,
      "divPerShare": 130.0,
      "exDivDate": "2026-12-29",
      "dividendYield": 3.45,
      "per": 31.4,
      "pbr": 1.28,
      "roe": 9.3,
      "rsi": 76.0,
      "vol": 0.2415,
      "inTop": false,
      "yutai": null
    },
    {
      "code": "4543.T",
      "name": "テルモ",
      "price": 2147.5,
      "divPerShare": 36.0,
      "exDivDate": "2026-09-29",
      "dividendYield": 1.64,
      "per": 23.3,
      "pbr": 2.0,
      "roe": 9.2,
      "rsi": 43.9,
      "vol": 0.3922,
      "inTop": false,
      "yutai": null
    },
    {
      "code": "6857.T",
      "name": "アドバンテスト",
      "price": 30990.0,
      "divPerShare": 60.0,
      "exDivDate": "2026-03-30",
      "dividendYield": 20.0,
      "per": 60.2,
      "pbr": 28.26,
      "roe": 57.6,
      "rsi": 56.7,
      "vol": 0.755,
      "inTop": false,
      "yutai": null
    },
    {
      "code": "7741.T",
      "name": "HOYA",
      "price": 24815.0,
      "divPerShare": 295.0,
      "exDivDate": "2026-03-30",
      "dividendYield": 1.18,
      "per": 33.4,
      "pbr": 8.16,
      "roe": 25.1,
      "rsi": 43.2,
      "vol": 0.3374,
      "inTop": false,
      "yutai": null
    },
    {
      "code": "6920.T",
      "name": "レーザーテック",
      "price": 45290.0,
      "divPerShare": 329.0,
      "exDivDate": "2026-06-29",
      "dividendYield": 0.77,
      "per": 46.8,
      "pbr": 18.0,
      "roe": 44.1,
      "rsi": 45.0,
      "vol": 0.7665,
      "inTop": false,
      "yutai": null
    },
    {
      "code": "7267.T",
      "name": "ホンダ",
      "price": 1559.0,
      "divPerShare": 70.0,
      "exDivDate": "2026-09-29",
      "dividendYield": 4.49,
      "per": null,
      "pbr": 0.51,
      "roe": -2.8,
      "rsi": 55.5,
      "vol": 0.3404,
      "inTop": false,
      "yutai": null
    },
    {
      "code": "6954.T",
      "name": "ファナック",
      "price": 6925.0,
      "divPerShare": 107.09,
      "exDivDate": "2026-03-30",
      "dividendYield": 1.56,
      "per": 38.8,
      "pbr": 3.47,
      "roe": 9.4,
      "rsi": 44.7,
      "vol": 0.5718,
      "inTop": false,
      "yutai": null
    },
    {
      "code": "7751.T",
      "name": "キヤノン",
      "price": 4518.0,
      "divPerShare": 160.0,
      "exDivDate": "2026-12-29",
      "dividendYield": 3.53,
      "per": 12.3,
      "pbr": 1.14,
      "roe": 9.4,
      "rsi": 78.5,
      "vol": 0.2249,
      "inTop": true,
      "yutai": null
    },
    {
      "code": "6971.T",
      "name": "京セラ",
      "price": 3723.0,
      "divPerShare": 56.0,
      "exDivDate": "2026-09-29",
      "dividendYield": 1.48,
      "per": 36.2,
      "pbr": 1.47,
      "roe": 4.4,
      "rsi": 40.6,
      "vol": 0.4106,
      "inTop": false,
      "yutai": null
    },
    {
      "code": "6367.T",
      "name": "ダイキン工業",
      "price": 24190.0,
      "divPerShare": 360.0,
      "exDivDate": "2026-09-29",
      "dividendYield": 1.49,
      "per": 25.8,
      "pbr": 2.18,
      "roe": 9.3,
      "rsi": 35.8,
      "vol": 0.4085,
      "inTop": false,
      "yutai": null
    },
    {
      "code": "6723.T",
      "name": "ルネサスエレクトロニクス",
      "price": 4222.0,
      "divPerShare": 28.0,
      "exDivDate": "2025-12-29",
      "dividendYield": 0.67,
      "per": null,
      "pbr": 3.01,
      "roe": -0.4,
      "rsi": 34.1,
      "vol": 0.7374,
      "inTop": false,
      "yutai": null
    },
    {
      "code": "6752.T",
      "name": "パナソニックHD",
      "price": 4050.0,
      "divPerShare": 54.0,
      "exDivDate": "2026-09-29",
      "dividendYield": 1.32,
      "per": 50.0,
      "pbr": 1.81,
      "roe": 4.1,
      "rsi": 31.7,
      "vol": 0.5086,
      "inTop": false,
      "yutai": null
    },
    {
      "code": "6770.T",
      "name": "アルプスアルパイン",
      "price": 2156.5,
      "divPerShare": 64.0,
      "exDivDate": "2026-09-29",
      "dividendYield": 3.01,
      "per": 16.0,
      "pbr": 0.94,
      "roe": 6.3,
      "rsi": 56.3,
      "vol": 0.4608,
      "inTop": false,
      "yutai": null
    },
    {
      "code": "7735.T",
      "name": "SCREENホールディングス",
      "price": 16825.0,
      "divPerShare": 175.0,
      "exDivDate": "2026-09-29",
      "dividendYield": 1.06,
      "per": 34.6,
      "pbr": 6.54,
      "roe": 20.3,
      "rsi": 43.5,
      "vol": 0.6996,
      "inTop": false,
      "yutai": null
    },
    {
      "code": "6146.T",
      "name": "ディスコ",
      "price": 70320.0,
      "divPerShare": 505.0,
      "exDivDate": "2026-03-30",
      "dividendYield": 0.74,
      "per": 56.3,
      "pbr": 12.98,
      "roe": 25.1,
      "rsi": 40.5,
      "vol": 0.6773,
      "inTop": false,
      "yutai": null
    },
    {
      "code": "4452.T",
      "name": "花王",
      "price": 3216.0,
      "divPerShare": 78.0,
      "exDivDate": "2026-12-29",
      "dividendYield": 2.41,
      "per": 27.7,
      "pbr": 2.71,
      "roe": 11.9,
      "rsi": 43.9,
      "vol": 0.2294,
      "inTop": false,
      "yutai": null
    },
    {
      "code": "4911.T",
      "name": "資生堂",
      "price": 3111.0,
      "divPerShare": 60.0,
      "exDivDate": "2026-12-29",
      "dividendYield": 1.97,
      "per": null,
      "pbr": 2.05,
      "roe": -5.6,
      "rsi": 71.5,
      "vol": 0.4602,
      "inTop": false,
      "yutai": null
    },
    {
      "code": "8306.T",
      "name": "三菱UFJ",
      "price": 3768.0,
      "divPerShare": 96.0,
      "exDivDate": "2026-09-29",
      "dividendYield": 2.62,
      "per": 17.7,
      "pbr": 2.17,
      "roe": 9.4,
      "rsi": 73.7,
      "vol": 0.3411,
      "inTop": true,
      "yutai": null
    },
    {
      "code": "8316.T",
      "name": "三井住友FG",
      "price": 7201.0,
      "divPerShare": 135.0,
      "exDivDate": "2026-09-29",
      "dividendYield": 1.91,
      "per": 17.5,
      "pbr": 1.73,
      "roe": 6.9,
      "rsi": 71.9,
      "vol": 0.3749,
      "inTop": false,
      "yutai": null
    },
    {
      "code": "8411.T",
      "name": "みずほFG",
      "price": 8802.0,
      "divPerShare": 150.0,
      "exDivDate": "2026-09-29",
      "dividendYield": 1.76,
      "per": 17.5,
      "pbr": 1.9,
      "roe": 11.4,
      "rsi": 68.1,
      "vol": 0.4621,
      "inTop": false,
      "yutai": null
    },
    {
      "code": "8604.T",
      "name": "野村HD",
      "price": 1616.0,
      "divPerShare": 51.0,
      "exDivDate": "2026-03-30",
      "dividendYield": 3.18,
      "per": 13.6,
      "pbr": 1.26,
      "roe": 10.1,
      "rsi": 69.5,
      "vol": 0.3865,
      "inTop": false,
      "yutai": null
    },
    {
      "code": "8630.T",
      "name": "SOMPOホールディングス",
      "price": 6965.0,
      "divPerShare": 200.0,
      "exDivDate": "2026-09-29",
      "dividendYield": 2.9,
      "per": 27.8,
      "pbr": 1.2,
      "roe": 13.5,
      "rsi": 68.1,
      "vol": 0.3531,
      "inTop": false,
      "yutai": null
    },
    {
      "code": "8725.T",
      "name": "MS&ADインシュアランス",
      "price": 4866.0,
      "divPerShare": 140.0,
      "exDivDate": "2026-09-29",
      "dividendYield": 2.92,
      "per": 14.2,
      "pbr": 1.1,
      "roe": 9.8,
      "rsi": 76.1,
      "vol": 0.2933,
      "inTop": true,
      "yutai": null
    },
    {
      "code": "8750.T",
      "name": "第一生命HD",
      "price": 1901.5,
      "divPerShare": 72.0,
      "exDivDate": "2026-09-29",
      "dividendYield": 3.8,
      "per": 15.7,
      "pbr": 1.61,
      "roe": 11.3,
      "rsi": 60.2,
      "vol": 0.3274,
      "inTop": false,
      "yutai": null
    },
    {
      "code": "8766.T",
      "name": "東京海上HD",
      "price": 7969.0,
      "divPerShare": 245.0,
      "exDivDate": "2026-09-29",
      "dividendYield": 3.07,
      "per": 28.6,
      "pbr": 1.88,
      "roe": 8.7,
      "rsi": 63.5,
      "vol": 0.4438,
      "inTop": false,
      "yutai": null
    },
    {
      "code": "7182.T",
      "name": "ゆうちょ銀行",
      "price": 3450.0,
      "divPerShare": 93.0,
      "exDivDate": "2027-03-30",
      "dividendYield": 2.73,
      "per": 23.5,
      "pbr": 1.33,
      "roe": 5.9,
      "rsi": 68.6,
      "vol": 0.4198,
      "inTop": false,
      "yutai": null
    },
    {
      "code": "8303.T",
      "name": "新生銀行",
      "price": 1455.5,
      "divPerShare": 42.0,
      "exDivDate": "2026-03-30",
      "dividendYield": 2.91,
      "per": 10.6,
      "pbr": 1.05,
      "roe": 10.3,
      "rsi": 57.3,
      "vol": 0.4211,
      "inTop": false,
      "yutai": null
    },
    {
      "code": "9984.T",
      "name": "ソフトバンクG",
      "price": 5870.0,
      "divPerShare": 11.0,
      "exDivDate": "2026-09-29",
      "dividendYield": 19.0,
      "per": 6.7,
      "pbr": 1.9,
      "roe": 32.7,
      "rsi": 44.5,
      "vol": 0.9315,
      "inTop": false,
      "yutai": null
    },
    {
      "code": "9432.T",
      "name": "NTT",
      "price": 149.6,
      "divPerShare": 5.4,
      "exDivDate": "2026-09-29",
      "dividendYield": 3.55,
      "per": 11.9,
      "pbr": 1.25,
      "roe": 10.0,
      "rsi": 64.0,
      "vol": 0.1341,
      "inTop": false,
      "yutai": "なし（過去はdポイント優待）"
    },
    {
      "code": "9433.T",
      "name": "KDDI",
      "price": 2856.0,
      "divPerShare": 84.0,
      "exDivDate": "2026-09-29",
      "dividendYield": 2.92,
      "per": 15.6,
      "pbr": 2.14,
      "roe": 14.0,
      "rsi": 73.9,
      "vol": 0.2634,
      "inTop": false,
      "yutai": "100株以上でカタログギフト等（長期保有優遇・要IR確認）"
    },
    {
      "code": "9434.T",
      "name": "ソフトバンク",
      "price": 218.9,
      "divPerShare": 8.8,
      "exDivDate": "2026-09-29",
      "dividendYield": 3.97,
      "per": 19.4,
      "pbr": 3.54,
      "roe": 16.3,
      "rsi": 68.3,
      "vol": 0.1594,
      "inTop": false,
      "yutai": null
    },
    {
      "code": "6098.T",
      "name": "リクルートHD",
      "price": 12245.0,
      "divPerShare": 26.0,
      "exDivDate": "2026-09-29",
      "dividendYield": 0.21,
      "per": 35.3,
      "pbr": 10.8,
      "roe": 30.8,
      "rsi": 60.4,
      "vol": 0.5232,
      "inTop": false,
      "yutai": null
    },
    {
      "code": "4307.T",
      "name": "野村総合研究所",
      "price": 4893.0,
      "divPerShare": 84.0,
      "exDivDate": "2026-09-29",
      "dividendYield": 1.69,
      "per": 185.3,
      "pbr": 6.48,
      "roe": 3.6,
      "rsi": 52.6,
      "vol": 0.5668,
      "inTop": false,
      "yutai": null
    },
    {
      "code": "9613.T",
      "name": "NTTデータグループ",
      "price": null,
      "divPerShare": null,
      "exDivDate": null,
      "dividendYield": null,
      "per": null,
      "pbr": null,
      "roe": null,
      "rsi": null,
      "vol": null,
      "inTop": false,
      "yutai": null
    },
    {
      "code": "4704.T",
      "name": "トレンドマイクロ",
      "price": 6151.0,
      "divPerShare": 185.0,
      "exDivDate": "2025-12-29",
      "dividendYield": 2.93,
      "per": 23.6,
      "pbr": 6.99,
      "roe": 33.8,
      "rsi": 43.9,
      "vol": 0.4818,
      "inTop": false,
      "yutai": null
    },
    {
      "code": "3659.T",
      "name": "ネクソン",
      "price": 2229.5,
      "divPerShare": 60.0,
      "exDivDate": "2026-12-29",
      "dividendYield": 2.69,
      "per": 19.5,
      "pbr": 1.66,
      "roe": 11.6,
      "rsi": 49.3,
      "vol": 0.4524,
      "inTop": false,
      "yutai": null
    },
    {
      "code": "9735.T",
      "name": "セコム",
      "price": 6641.0,
      "divPerShare": 120.0,
      "exDivDate": "2026-09-29",
      "dividendYield": 1.78,
      "per": 24.0,
      "pbr": 2.04,
      "roe": 8.7,
      "rsi": 63.5,
      "vol": 0.2335,
      "inTop": false,
      "yutai": null
    },
    {
      "code": "4519.T",
      "name": "中外製薬",
      "price": 7188.0,
      "divPerShare": 132.0,
      "exDivDate": "2026-12-29",
      "dividendYield": 1.81,
      "per": 27.3,
      "pbr": 6.2,
      "roe": 23.7,
      "rsi": 42.2,
      "vol": 0.4476,
      "inTop": false,
      "yutai": null
    },
    {
      "code": "4502.T",
      "name": "武田薬品工業",
      "price": 5482.0,
      "divPerShare": 204.0,
      "exDivDate": "2026-09-29",
      "dividendYield": 3.67,
      "per": null,
      "pbr": 1.17,
      "roe": -2.1,
      "rsi": 62.4,
      "vol": 0.2314,
      "inTop": false,
      "yutai": null
    },
    {
      "code": "4568.T",
      "name": "第一三共",
      "price": 2755.0,
      "divPerShare": 100.0,
      "exDivDate": "2026-09-29",
      "dividendYield": 3.62,
      "per": 19.6,
      "pbr": 3.01,
      "roe": 15.8,
      "rsi": 63.3,
      "vol": 0.3709,
      "inTop": false,
      "yutai": null
    },
    {
      "code": "4523.T",
      "name": "エーザイ",
      "price": 4565.0,
      "divPerShare": 160.0,
      "exDivDate": "2026-09-29",
      "dividendYield": 3.52,
      "per": 33.3,
      "pbr": 1.43,
      "roe": 4.5,
      "rsi": 72.0,
      "vol": 0.3181,
      "inTop": false,
      "yutai": null
    },
    {
      "code": "4506.T",
      "name": "住友ファーマ",
      "price": 1288.5,
      "divPerShare": null,
      "exDivDate": "2023-03-30",
      "dividendYield": null,
      "per": 4.8,
      "pbr": 1.75,
      "roe": 46.3,
      "rsi": 26.4,
      "vol": 0.7646,
      "inTop": false,
      "yutai": null
    },
    {
      "code": "4021.T",
      "name": "日産化学",
      "price": 7835.0,
      "divPerShare": 212.0,
      "exDivDate": "2026-09-29",
      "dividendYield": 2.69,
      "per": 21.3,
      "pbr": 4.12,
      "roe": 20.4,
      "rsi": 32.3,
      "vol": 0.4059,
      "inTop": false,
      "yutai": null
    },
    {
      "code": "7832.T",
      "name": "バンダイナムコHD",
      "price": 4067.0,
      "divPerShare": 48.0,
      "exDivDate": "2026-09-29",
      "dividendYield": 1.17,
      "per": 18.7,
      "pbr": 3.03,
      "roe": 17.0,
      "rsi": 63.5,
      "vol": 0.2706,
      "inTop": false,
      "yutai": null
    },
    {
      "code": "8058.T",
      "name": "三菱商事",
      "price": 4927.0,
      "divPerShare": 125.0,
      "exDivDate": "2026-09-29",
      "dividendYield": 2.56,
      "per": 23.5,
      "pbr": 1.91,
      "roe": 9.0,
      "rsi": 76.7,
      "vol": 0.4051,
      "inTop": false,
      "yutai": null
    },
    {
      "code": "8031.T",
      "name": "三井物産",
      "price": 4958.0,
      "divPerShare": 140.0,
      "exDivDate": "2026-09-29",
      "dividendYield": 2.85,
      "per": 17.1,
      "pbr": 1.6,
      "roe": 10.3,
      "rsi": 70.9,
      "vol": 0.4025,
      "inTop": false,
      "yutai": null
    },
    {
      "code": "8001.T",
      "name": "伊藤忠商事",
      "price": 1977.0,
      "divPerShare": 44.0,
      "exDivDate": "2026-09-29",
      "dividendYield": 2.24,
      "per": 15.4,
      "pbr": 2.1,
      "roe": 13.9,
      "rsi": 69.1,
      "vol": 0.2864,
      "inTop": false,
      "yutai": null
    },
    {
      "code": "8002.T",
      "name": "丸紅",
      "price": 5395.0,
      "divPerShare": 115.0,
      "exDivDate": "2026-09-29",
      "dividendYield": 2.19,
      "per": 16.3,
      "pbr": 2.03,
      "roe": 13.5,
      "rsi": 74.4,
      "vol": 0.4279,
      "inTop": false,
      "yutai": null
    },
    {
      "code": "8053.T",
      "name": "住友商事",
      "price": 1628.5,
      "divPerShare": 40.0,
      "exDivDate": "2026-09-29",
      "dividendYield": 2.49,
      "per": 13.1,
      "pbr": 1.68,
      "roe": 13.5,
      "rsi": 56.9,
      "vol": 0.4643,
      "inTop": false,
      "yutai": null
    },
    {
      "code": "8015.T",
      "name": "豊田通商",
      "price": 6572.0,
      "divPerShare": 125.0,
      "exDivDate": "2026-09-29",
      "dividendYield": 1.94,
      "per": 18.7,
      "pbr": 2.2,
      "roe": 13.2,
      "rsi": 67.1,
      "vol": 0.4754,
      "inTop": false,
      "yutai": null
    },
    {
      "code": "8801.T",
      "name": "三井不動産",
      "price": 1545.5,
      "divPerShare": 37.0,
      "exDivDate": "2026-09-29",
      "dividendYield": 2.38,
      "per": 15.3,
      "pbr": 1.28,
      "roe": 8.2,
      "rsi": 56.8,
      "vol": 0.3591,
      "inTop": false,
      "yutai": "保有株数に応じ宿泊優待割引券（要IR確認・手動更新）"
    },
    {
      "code": "8802.T",
      "name": "三菱地所",
      "price": 4075.0,
      "divPerShare": 50.0,
      "exDivDate": "2026-09-29",
      "dividendYield": 1.19,
      "per": 22.4,
      "pbr": 1.83,
      "roe": 8.4,
      "rsi": 49.3,
      "vol": 0.4119,
      "inTop": false,
      "yutai": null
    },
    {
      "code": "8830.T",
      "name": "住友不動産",
      "price": 3689.0,
      "divPerShare": 52.0,
      "exDivDate": "2026-09-29",
      "dividendYield": 1.37,
      "per": 16.2,
      "pbr": 1.38,
      "roe": 9.2,
      "rsi": 47.3,
      "vol": 0.419,
      "inTop": false,
      "yutai": null
    },
    {
      "code": "3003.T",
      "name": "ヒューリック",
      "price": 1779.0,
      "divPerShare": 67.0,
      "exDivDate": "2026-12-29",
      "dividendYield": 3.71,
      "per": 11.8,
      "pbr": 1.49,
      "roe": 13.0,
      "rsi": 63.9,
      "vol": 0.2486,
      "inTop": false,
      "yutai": null
    },
    {
      "code": "8955.T",
      "name": "日本プライムリアルティ投資法人",
      "price": 97100.0,
      "divPerShare": 4250.0,
      "exDivDate": "2026-06-29",
      "dividendYield": 4.36,
      "per": 19.5,
      "pbr": 0.36,
      "roe": 7.1,
      "rsi": 70.3,
      "vol": 0.1546,
      "inTop": false,
      "yutai": null
    },
    {
      "code": "5020.T",
      "name": "ENEOS",
      "price": 1334.5,
      "divPerShare": 34.0,
      "exDivDate": "2026-09-29",
      "dividendYield": 2.58,
      "per": 13.9,
      "pbr": 1.07,
      "roe": 8.5,
      "rsi": 74.5,
      "vol": 0.3902,
      "inTop": false,
      "yutai": null
    },
    {
      "code": "5019.T",
      "name": "出光興産",
      "price": 1325.0,
      "divPerShare": 36.0,
      "exDivDate": "2026-09-29",
      "dividendYield": 2.74,
      "per": 9.4,
      "pbr": 0.84,
      "roe": 9.0,
      "rsi": 77.6,
      "vol": 0.3594,
      "inTop": false,
      "yutai": null
    },
    {
      "code": "9501.T",
      "name": "東京電力HD",
      "price": 515.8,
      "divPerShare": null,
      "exDivDate": "2011-03-29",
      "dividendYield": null,
      "per": null,
      "pbr": 0.24,
      "roe": -12.6,
      "rsi": 81.2,
      "vol": 0.5394,
      "inTop": true,
      "yutai": null
    },
    {
      "code": "9502.T",
      "name": "中部電力",
      "price": 2970.5,
      "divPerShare": 70.0,
      "exDivDate": "2026-09-29",
      "dividendYield": 2.36,
      "per": 9.9,
      "pbr": 0.72,
      "roe": 7.7,
      "rsi": 42.0,
      "vol": 0.3336,
      "inTop": false,
      "yutai": null
    },
    {
      "code": "9503.T",
      "name": "関西電力",
      "price": 2354.5,
      "divPerShare": 80.0,
      "exDivDate": "2026-09-29",
      "dividendYield": 3.4,
      "per": 6.9,
      "pbr": 0.76,
      "roe": 11.6,
      "rsi": 61.9,
      "vol": 0.3144,
      "inTop": false,
      "yutai": null
    },
    {
      "code": "9531.T",
      "name": "東京ガス",
      "price": 6147.0,
      "divPerShare": 120.0,
      "exDivDate": "2026-09-29",
      "dividendYield": 1.95,
      "per": 9.4,
      "pbr": 1.19,
      "roe": 12.8,
      "rsi": 59.9,
      "vol": 0.3043,
      "inTop": false,
      "yutai": null
    },
    {
      "code": "9101.T",
      "name": "日本郵船",
      "price": 5785.0,
      "divPerShare": 200.0,
      "exDivDate": "2026-09-29",
      "dividendYield": 3.44,
      "per": 11.5,
      "pbr": 0.76,
      "roe": 7.1,
      "rsi": 72.8,
      "vol": 0.296,
      "inTop": true,
      "yutai": "なし（日本郵船は株主優待制度なし）"
    },
    {
      "code": "9104.T",
      "name": "商船三井",
      "price": 5772.0,
      "divPerShare": 205.0,
      "exDivDate": "2026-09-29",
      "dividendYield": 3.54,
      "per": 9.3,
      "pbr": 0.69,
      "roe": 7.6,
      "rsi": 75.8,
      "vol": 0.3673,
      "inTop": false,
      "yutai": null
    },
    {
      "code": "9107.T",
      "name": "川崎汽船",
      "price": 2779.0,
      "divPerShare": 120.0,
      "exDivDate": "2026-09-29",
      "dividendYield": 4.34,
      "per": 13.2,
      "pbr": 0.97,
      "roe": 7.8,
      "rsi": 72.2,
      "vol": 0.3524,
      "inTop": true,
      "yutai": null
    },
    {
      "code": "9983.T",
      "name": "ファーストリテイリング",
      "price": 77240.0,
      "divPerShare": 640.0,
      "exDivDate": "2026-08-28",
      "dividendYield": 0.81,
      "per": 49.6,
      "pbr": 8.69,
      "roe": 22.5,
      "rsi": 37.5,
      "vol": 0.3522,
      "inTop": false,
      "yutai": null
    },
    {
      "code": "3038.T",
      "name": "神戸物産",
      "price": 2626.5,
      "divPerShare": 32.0,
      "exDivDate": "2026-10-29",
      "dividendYield": 1.22,
      "per": 17.2,
      "pbr": 3.38,
      "roe": 21.7,
      "rsi": 46.1,
      "vol": 0.3139,
      "inTop": false,
      "yutai": null
    },
    {
      "code": "4661.T",
      "name": "オリエンタルランド",
      "price": 2615.5,
      "divPerShare": 16.0,
      "exDivDate": "2026-09-29",
      "dividendYield": 0.6,
      "per": 35.2,
      "pbr": 3.9,
      "roe": 11.7,
      "rsi": 59.3,
      "vol": 0.3214,
      "inTop": false,
      "yutai": null
    },
    {
      "code": "7974.T",
      "name": "任天堂",
      "price": 6950.0,
      "divPerShare": 219.0,
      "exDivDate": "2026-03-30",
      "dividendYield": 3.13,
      "per": 19.0,
      "pbr": 2.71,
      "roe": 14.9,
      "rsi": 42.3,
      "vol": 0.4205,
      "inTop": false,
      "yutai": "なし（任天堂は株主優待制度なし）"
    },
    {
      "code": "2914.T",
      "name": "JT",
      "price": 6378.0,
      "divPerShare": 242.0,
      "exDivDate": "2026-12-29",
      "dividendYield": 3.75,
      "per": 22.7,
      "pbr": 2.77,
      "roe": 13.6,
      "rsi": 69.0,
      "vol": 0.2329,
      "inTop": false,
      "yutai": "100株以上でJT関連商品の詰め合わせ（年1回・要IR確認）"
    },
    {
      "code": "2502.T",
      "name": "アサヒグループHD",
      "price": 1619.0,
      "divPerShare": 62.0,
      "exDivDate": "2026-12-29",
      "dividendYield": 3.8,
      "per": 19.9,
      "pbr": 0.79,
      "roe": 4.3,
      "rsi": 62.6,
      "vol": 0.2143,
      "inTop": false,
      "yutai": null
    },
    {
      "code": "2503.T",
      "name": "キリンHD",
      "price": 2894.0,
      "divPerShare": 76.0,
      "exDivDate": "2026-12-29",
      "dividendYield": 2.62,
      "per": 15.9,
      "pbr": 1.77,
      "roe": 12.2,
      "rsi": 66.0,
      "vol": 0.2695,
      "inTop": false,
      "yutai": null
    },
    {
      "code": "2802.T",
      "name": "味の素",
      "price": 5106.0,
      "divPerShare": 50.0,
      "exDivDate": "2026-09-29",
      "dividendYield": 0.95,
      "per": 37.0,
      "pbr": 6.35,
      "roe": 17.5,
      "rsi": 17.6,
      "vol": 0.4995,
      "inTop": false,
      "yutai": null
    },
    {
      "code": "7201.T",
      "name": "日産自動車",
      "price": 331.0,
      "divPerShare": null,
      "exDivDate": "2024-03-28",
      "dividendYield": null,
      "per": null,
      "pbr": 0.24,
      "roe": -9.9,
      "rsi": 63.4,
      "vol": 0.4268,
      "inTop": true,
      "yutai": null
    },
    {
      "code": "2269.T",
      "name": "明治HD",
      "price": 3699.0,
      "divPerShare": 110.0,
      "exDivDate": "2026-09-29",
      "dividendYield": 2.95,
      "per": 28.6,
      "pbr": 1.3,
      "roe": 4.8,
      "rsi": 39.6,
      "vol": 0.2099,
      "inTop": false,
      "yutai": null
    },
    {
      "code": "3382.T",
      "name": "セブン＆アイHD",
      "price": 2066.5,
      "divPerShare": 60.0,
      "exDivDate": "2026-08-28",
      "dividendYield": 2.87,
      "per": 17.4,
      "pbr": 1.29,
      "roe": 8.0,
      "rsi": 59.0,
      "vol": 0.2618,
      "inTop": false,
      "yutai": null
    },
    {
      "code": "8267.T",
      "name": "イオン",
      "price": 1334.5,
      "divPerShare": 14.0,
      "exDivDate": "2026-08-28",
      "dividendYield": 1.03,
      "per": 49.6,
      "pbr": 3.05,
      "roe": 7.2,
      "rsi": 47.3,
      "vol": 0.3543,
      "inTop": false,
      "yutai": null
    },
    {
      "code": "9201.T",
      "name": "日本航空",
      "price": 2859.5,
      "divPerShare": 96.0,
      "exDivDate": "2026-09-29",
      "dividendYield": 3.35,
      "per": 9.3,
      "pbr": 0.95,
      "roe": 12.3,
      "rsi": 30.1,
      "vol": 0.328,
      "inTop": false,
      "yutai": null
    },
    {
      "code": "9202.T",
      "name": "ANAホールディングス",
      "price": 3005.0,
      "divPerShare": 60.0,
      "exDivDate": "2026-09-29",
      "dividendYield": 2.0,
      "per": 9.4,
      "pbr": 0.91,
      "roe": 12.9,
      "rsi": 41.0,
      "vol": 0.2894,
      "inTop": false,
      "yutai": null
    },
    {
      "code": "4751.T",
      "name": "サイバーエージェント",
      "price": 1399.0,
      "divPerShare": 19.0,
      "exDivDate": "2026-09-29",
      "dividendYield": 1.35,
      "per": 17.4,
      "pbr": 3.57,
      "roe": 21.1,
      "rsi": 46.0,
      "vol": 0.4254,
      "inTop": false,
      "yutai": null
    },
    {
      "code": "6753.T",
      "name": "シャープ",
      "price": 612.2,
      "divPerShare": null,
      "exDivDate": "2022-03-30",
      "dividendYield": null,
      "per": 8.4,
      "pbr": 1.41,
      "roe": 20.9,
      "rsi": 32.6,
      "vol": 0.5073,
      "inTop": false,
      "yutai": null
    },
    {
      "code": "7270.T",
      "name": "SUBARU",
      "price": 2600.0,
      "divPerShare": 116.0,
      "exDivDate": "2026-09-29",
      "dividendYield": 4.49,
      "per": 20.7,
      "pbr": 0.67,
      "roe": 3.3,
      "rsi": 64.0,
      "vol": 0.3494,
      "inTop": false,
      "yutai": null
    },
    {
      "code": "5714.T",
      "name": "DOWAホールディングス",
      "price": 8567.0,
      "divPerShare": 338.0,
      "exDivDate": "2027-03-30",
      "dividendYield": 4.0,
      "per": 8.2,
      "pbr": 1.11,
      "roe": 14.5,
      "rsi": 45.3,
      "vol": 0.605,
      "inTop": false,
      "yutai": null
    },
    {
      "code": "5401.T",
      "name": "日本製鉄",
      "price": 609.4,
      "divPerShare": 24.0,
      "exDivDate": "2026-09-29",
      "dividendYield": 4.01,
      "per": 185.2,
      "pbr": 0.58,
      "roe": 0.8,
      "rsi": 88.5,
      "vol": 0.2669,
      "inTop": true,
      "yutai": null
    },
    {
      "code": "5411.T",
      "name": "JFEホールディングス",
      "price": 1732.5,
      "divPerShare": 80.0,
      "exDivDate": "2026-03-30",
      "dividendYield": 4.67,
      "per": 16.4,
      "pbr": 0.42,
      "roe": 2.8,
      "rsi": 79.0,
      "vol": 0.2726,
      "inTop": true,
      "yutai": null
    },
    {
      "code": "3436.T",
      "name": "SUMCO",
      "price": 3791.0,
      "divPerShare": 20.0,
      "exDivDate": "2026-06-29",
      "dividendYield": 0.53,
      "per": null,
      "pbr": 2.33,
      "roe": -3.5,
      "rsi": 39.7,
      "vol": 0.9959,
      "inTop": false,
      "yutai": null
    },
    {
      "code": "4385.T",
      "name": "メルカリ",
      "price": 4412.0,
      "divPerShare": null,
      "exDivDate": null,
      "dividendYield": null,
      "per": 25.4,
      "pbr": 6.06,
      "roe": 33.0,
      "rsi": 59.4,
      "vol": 0.4859,
      "inTop": false,
      "yutai": null
    },
    {
      "code": "4565.T",
      "name": "ネクセラファーマ",
      "price": 904.0,
      "divPerShare": null,
      "exDivDate": "2015-03-27",
      "dividendYield": null,
      "per": null,
      "pbr": 1.28,
      "roe": -15.3,
      "rsi": 38.5,
      "vol": 0.5601,
      "inTop": false,
      "yutai": null
    },
    {
      "code": "3692.T",
      "name": "FFRIセキュリティ",
      "price": 5010.0,
      "divPerShare": 18.0,
      "exDivDate": "2027-03-30",
      "dividendYield": 0.36,
      "per": 36.0,
      "pbr": 10.49,
      "roe": 33.5,
      "rsi": 45.4,
      "vol": 0.6612,
      "inTop": false,
      "yutai": null
    },
    {
      "code": "4180.T",
      "name": "Appier Group",
      "price": 876.0,
      "divPerShare": 2.3,
      "exDivDate": "2026-12-29",
      "dividendYield": 0.26,
      "per": 35.0,
      "pbr": 2.37,
      "roe": 7.4,
      "rsi": 50.6,
      "vol": 0.6882,
      "inTop": false,
      "yutai": null
    },
    {
      "code": "4493.T",
      "name": "サイバーセキュリティクラウド",
      "price": 1814.0,
      "divPerShare": 6.0,
      "exDivDate": "2026-12-29",
      "dividendYield": 0.33,
      "per": 22.3,
      "pbr": 4.01,
      "roe": 22.1,
      "rsi": 48.4,
      "vol": 0.4737,
      "inTop": false,
      "yutai": null
    },
    {
      "code": "7779.T",
      "name": "サイバーダイン",
      "price": 227.0,
      "divPerShare": null,
      "exDivDate": null,
      "dividendYield": null,
      "per": 311.0,
      "pbr": 1.21,
      "roe": 0.4,
      "rsi": 46.3,
      "vol": 0.7513,
      "inTop": false,
      "yutai": null
    },
    {
      "code": "4382.T",
      "name": "HEROZ",
      "price": 703.0,
      "divPerShare": null,
      "exDivDate": null,
      "dividendYield": null,
      "per": 30.9,
      "pbr": 2.11,
      "roe": 11.2,
      "rsi": 44.6,
      "vol": 0.4113,
      "inTop": false,
      "yutai": null
    },
    {
      "code": "4478.T",
      "name": "freee",
      "price": 2320.0,
      "divPerShare": null,
      "exDivDate": null,
      "dividendYield": null,
      "per": 157.7,
      "pbr": 6.75,
      "roe": 3.5,
      "rsi": 65.0,
      "vol": 0.7347,
      "inTop": false,
      "yutai": null
    },
    {
      "code": "3923.T",
      "name": "ラクス",
      "price": 959.6,
      "divPerShare": 8.0,
      "exDivDate": "2027-03-30",
      "dividendYield": 0.82,
      "per": 26.0,
      "pbr": 13.05,
      "roe": 55.4,
      "rsi": 37.1,
      "vol": 0.5976,
      "inTop": false,
      "yutai": null
    },
    {
      "code": "4443.T",
      "name": "Sansan",
      "price": 1767.0,
      "divPerShare": 5.0,
      "exDivDate": "2026-11-27",
      "dividendYield": 0.28,
      "per": 109.7,
      "pbr": 10.61,
      "roe": 36.5,
      "rsi": 58.4,
      "vol": 0.6304,
      "inTop": false,
      "yutai": null
    },
    {
      "code": "5253.T",
      "name": "カバー",
      "price": 1561.0,
      "divPerShare": null,
      "exDivDate": null,
      "dividendYield": null,
      "per": 34.7,
      "pbr": 5.13,
      "roe": 16.3,
      "rsi": 59.4,
      "vol": 0.5975,
      "inTop": false,
      "yutai": null
    },
    {
      "code": "4480.T",
      "name": "メドレー",
      "price": 2008.0,
      "divPerShare": null,
      "exDivDate": null,
      "dividendYield": null,
      "per": 66.1,
      "pbr": 4.62,
      "roe": 6.3,
      "rsi": 44.8,
      "vol": 0.4701,
      "inTop": false,
      "yutai": null
    },
    {
      "code": "3994.T",
      "name": "マネーフォワード",
      "price": 5155.0,
      "divPerShare": null,
      "exDivDate": null,
      "dividendYield": null,
      "per": 65.9,
      "pbr": 6.42,
      "roe": 8.6,
      "rsi": 69.3,
      "vol": 0.7704,
      "inTop": false,
      "yutai": null
    },
    {
      "code": "6521.T",
      "name": "オキサイド",
      "price": 3440.0,
      "divPerShare": null,
      "exDivDate": null,
      "dividendYield": null,
      "per": null,
      "pbr": 8.33,
      "roe": -3.9,
      "rsi": 28.8,
      "vol": 1.0853,
      "inTop": false,
      "yutai": null
    },
    {
      "code": "4051.T",
      "name": "GMOフィナンシャルゲート",
      "price": 6400.0,
      "divPerShare": 125.0,
      "exDivDate": "2026-09-29",
      "dividendYield": 1.92,
      "per": 32.1,
      "pbr": 8.14,
      "roe": 26.1,
      "rsi": 19.6,
      "vol": 0.3817,
      "inTop": false,
      "yutai": null
    },
    {
      "code": "7342.T",
      "name": "ウェルスナビ",
      "price": null,
      "divPerShare": null,
      "exDivDate": null,
      "dividendYield": null,
      "per": null,
      "pbr": null,
      "roe": null,
      "rsi": null,
      "vol": null,
      "inTop": false,
      "yutai": null
    },
    {
      "code": "4485.T",
      "name": "JTOWER",
      "price": null,
      "divPerShare": null,
      "exDivDate": null,
      "dividendYield": null,
      "per": null,
      "pbr": null,
      "roe": null,
      "rsi": null,
      "vol": null,
      "inTop": false,
      "yutai": null
    },
    {
      "code": "6526.T",
      "name": "ソシオネクスト",
      "price": 2502.5,
      "divPerShare": 50.0,
      "exDivDate": "2026-09-29",
      "dividendYield": 2.01,
      "per": 50.6,
      "pbr": 3.3,
      "roe": 6.5,
      "rsi": 40.9,
      "vol": 0.6834,
      "inTop": false,
      "yutai": null
    },
    {
      "code": "6532.T",
      "name": "ベイカレント・コンサルティング",
      "price": 6216.0,
      "divPerShare": 130.0,
      "exDivDate": "2026-08-28",
      "dividendYield": 2.09,
      "per": 24.9,
      "pbr": 8.47,
      "roe": 38.6,
      "rsi": 42.0,
      "vol": 0.6504,
      "inTop": false,
      "yutai": null
    },
    {
      "code": "6038.T",
      "name": "イード",
      "price": 820.0,
      "divPerShare": 23.0,
      "exDivDate": "2026-06-29",
      "dividendYield": 2.79,
      "per": 9.0,
      "pbr": 0.8,
      "roe": 7.0,
      "rsi": 67.7,
      "vol": 0.1698,
      "inTop": false,
      "yutai": null
    },
    {
      "code": "4425.T",
      "name": "Kudan",
      "price": 1839.0,
      "divPerShare": null,
      "exDivDate": null,
      "dividendYield": null,
      "per": null,
      "pbr": 7.87,
      "roe": -6.5,
      "rsi": 44.9,
      "vol": 0.8949,
      "inTop": false,
      "yutai": null
    },
    {
      "code": "6027.T",
      "name": "弁護士ドットコム",
      "price": 2234.0,
      "divPerShare": null,
      "exDivDate": null,
      "dividendYield": null,
      "per": 33.8,
      "pbr": 7.09,
      "roe": 23.9,
      "rsi": 27.3,
      "vol": 0.505,
      "inTop": false,
      "yutai": null
    },
    {
      "code": "3696.T",
      "name": "セレス",
      "price": 2120.0,
      "divPerShare": 180.0,
      "exDivDate": "2026-12-29",
      "dividendYield": 8.42,
      "per": 9.8,
      "pbr": 1.85,
      "roe": 14.0,
      "rsi": 39.7,
      "vol": 0.6067,
      "inTop": false,
      "yutai": null
    },
    {
      "code": "2181.T",
      "name": "パーソルホールディングス",
      "price": 257.9,
      "divPerShare": 13.0,
      "exDivDate": "2026-09-29",
      "dividendYield": 5.01,
      "per": 13.4,
      "pbr": 2.62,
      "roe": 20.1,
      "rsi": 57.4,
      "vol": 0.2539,
      "inTop": false,
      "yutai": "なし（パーソルHDは株主優待制度なし・配当のみ）"
    },
    {
      "code": "7011.T",
      "name": "三菱重工業",
      "price": 3916.0,
      "divPerShare": 30.0,
      "exDivDate": "2026-09-29",
      "dividendYield": 0.77,
      "per": 37.4,
      "pbr": 4.26,
      "roe": 12.6,
      "rsi": 55.4,
      "vol": 0.4319,
      "inTop": false,
      "yutai": null
    },
    {
      "code": "7012.T",
      "name": "川崎重工業",
      "price": 2788.5,
      "divPerShare": 40.0,
      "exDivDate": "2026-09-29",
      "dividendYield": 1.46,
      "per": 21.5,
      "pbr": 2.65,
      "roe": 13.7,
      "rsi": 51.2,
      "vol": 0.6051,
      "inTop": false,
      "yutai": null
    },
    {
      "code": "7013.T",
      "name": "IHI",
      "price": 2897.0,
      "divPerShare": 23.0,
      "exDivDate": "2026-09-29",
      "dividendYield": 0.83,
      "per": 19.1,
      "pbr": 4.71,
      "roe": 27.8,
      "rsi": 55.2,
      "vol": 0.5505,
      "inTop": false,
      "yutai": null
    },
    {
      "code": "6273.T",
      "name": "SMC",
      "price": 73180.0,
      "divPerShare": 1000.0,
      "exDivDate": "2026-09-29",
      "dividendYield": 1.39,
      "per": 27.8,
      "pbr": 2.18,
      "roe": 8.3,
      "rsi": 50.9,
      "vol": 0.5493,
      "inTop": false,
      "yutai": null
    },
    {
      "code": "6594.T",
      "name": "ニデック",
      "price": 2548.0,
      "divPerShare": 40.0,
      "exDivDate": "2026-03-30",
      "dividendYield": 1.92,
      "per": 24.3,
      "pbr": 1.66,
      "roe": 6.3,
      "rsi": 40.7,
      "vol": 0.5252,
      "inTop": false,
      "yutai": null
    },
    {
      "code": "8593.T",
      "name": "三菱HCキャピタル",
      "price": 1436.0,
      "divPerShare": 52.0,
      "exDivDate": "2026-09-29",
      "dividendYield": 3.62,
      "per": 12.7,
      "pbr": 1.04,
      "roe": 8.5,
      "rsi": 76.1,
      "vol": 0.235,
      "inTop": false,
      "yutai": null
    },
    {
      "code": "8697.T",
      "name": "日本取引所グループ",
      "price": 2269.0,
      "divPerShare": 61.0,
      "exDivDate": "2026-09-29",
      "dividendYield": 2.75,
      "per": 38.6,
      "pbr": 6.76,
      "roe": 23.0,
      "rsi": 62.8,
      "vol": 0.4003,
      "inTop": false,
      "yutai": null
    },
    {
      "code": "9020.T",
      "name": "JR東日本",
      "price": 3566.0,
      "divPerShare": 84.0,
      "exDivDate": "2026-09-29",
      "dividendYield": 2.32,
      "per": 16.2,
      "pbr": 1.32,
      "roe": 8.4,
      "rsi": 66.4,
      "vol": 0.2692,
      "inTop": false,
      "yutai": null
    },
    {
      "code": "9022.T",
      "name": "JR東海",
      "price": 3821.0,
      "divPerShare": 32.0,
      "exDivDate": "2026-09-29",
      "dividendYield": 0.84,
      "per": 6.7,
      "pbr": 0.72,
      "roe": 11.5,
      "rsi": 78.8,
      "vol": 0.2965,
      "inTop": false,
      "yutai": null
    },
    {
      "code": "6301.T",
      "name": "小松製作所",
      "price": 6633.0,
      "divPerShare": 190.0,
      "exDivDate": "2026-09-29",
      "dividendYield": 2.95,
      "per": 16.0,
      "pbr": 1.7,
      "roe": 11.4,
      "rsi": 58.7,
      "vol": 0.4754,
      "inTop": false,
      "yutai": null
    },
    {
      "code": "6305.T",
      "name": "日立建機",
      "price": 5435.0,
      "divPerShare": 190.0,
      "exDivDate": "2026-09-29",
      "dividendYield": 3.59,
      "per": 15.8,
      "pbr": 1.28,
      "roe": 9.1,
      "rsi": 59.9,
      "vol": 0.4247,
      "inTop": false,
      "yutai": null
    },
    {
      "code": "7269.T",
      "name": "スズキ",
      "price": 2044.5,
      "divPerShare": 52.0,
      "exDivDate": "2026-09-29",
      "dividendYield": 2.53,
      "per": 9.0,
      "pbr": 1.17,
      "roe": 13.9,
      "rsi": 46.8,
      "vol": 0.3736,
      "inTop": false,
      "yutai": null
    },
    {
      "code": "7261.T",
      "name": "マツダ",
      "price": 1159.0,
      "divPerShare": 55.0,
      "exDivDate": "2026-09-29",
      "dividendYield": 4.74,
      "per": 20.8,
      "pbr": 0.38,
      "roe": 1.9,
      "rsi": 60.0,
      "vol": 0.4099,
      "inTop": false,
      "yutai": null
    },
    {
      "code": "6981.T",
      "name": "村田製作所",
      "price": 8683.0,
      "divPerShare": 70.0,
      "exDivDate": "2026-09-29",
      "dividendYield": 0.84,
      "per": 68.2,
      "pbr": 5.81,
      "roe": 8.8,
      "rsi": 33.0,
      "vol": 0.832,
      "inTop": false,
      "yutai": null
    },
    {
      "code": "6762.T",
      "name": "TDK",
      "price": 3125.0,
      "divPerShare": 40.0,
      "exDivDate": "2026-09-29",
      "dividendYield": 1.29,
      "per": 30.4,
      "pbr": 2.71,
      "roe": 9.9,
      "rsi": 27.6,
      "vol": 0.6444,
      "inTop": false,
      "yutai": null
    },
    {
      "code": "6503.T",
      "name": "三菱電機",
      "price": 5733.0,
      "divPerShare": 60.0,
      "exDivDate": "2026-09-29",
      "dividendYield": 1.07,
      "per": 28.9,
      "pbr": 2.62,
      "roe": 10.0,
      "rsi": 44.9,
      "vol": 0.456,
      "inTop": false,
      "yutai": null
    },
    {
      "code": "5802.T",
      "name": "住友電気工業",
      "price": 2528.5,
      "divPerShare": 39.0,
      "exDivDate": "2026-09-29",
      "dividendYield": 1.59,
      "per": 21.4,
      "pbr": 2.88,
      "roe": 15.0,
      "rsi": 43.9,
      "vol": 0.7978,
      "inTop": false,
      "yutai": null
    },
    {
      "code": "4901.T",
      "name": "富士フイルムHD",
      "price": 3657.0,
      "divPerShare": 75.0,
      "exDivDate": "2026-09-29",
      "dividendYield": 2.05,
      "per": 15.9,
      "pbr": 1.15,
      "roe": 7.7,
      "rsi": 66.4,
      "vol": 0.2917,
      "inTop": false,
      "yutai": null
    },
    {
      "code": "4578.T",
      "name": "大塚ホールディングス",
      "price": 10900.0,
      "divPerShare": 140.0,
      "exDivDate": "2026-12-29",
      "dividendYield": 1.28,
      "per": 15.9,
      "pbr": 1.85,
      "roe": 12.9,
      "rsi": 33.1,
      "vol": 0.3447,
      "inTop": false,
      "yutai": null
    },
    {
      "code": "4507.T",
      "name": "塩野義製薬",
      "price": 2833.5,
      "divPerShare": 76.0,
      "exDivDate": "2026-09-29",
      "dividendYield": 2.64,
      "per": 11.8,
      "pbr": 1.43,
      "roe": 13.5,
      "rsi": 56.2,
      "vol": 0.2848,
      "inTop": false,
      "yutai": null
    },
    {
      "code": "6178.T",
      "name": "日本郵政",
      "price": 2464.0,
      "divPerShare": 60.0,
      "exDivDate": "2026-09-29",
      "dividendYield": 2.45,
      "per": 19.1,
      "pbr": 0.71,
      "roe": 4.7,
      "rsi": 73.4,
      "vol": 0.3147,
      "inTop": true,
      "yutai": null
    },
    {
      "code": "2801.T",
      "name": "キッコーマン",
      "price": 1601.5,
      "divPerShare": 25.0,
      "exDivDate": "2026-09-29",
      "dividendYield": 1.54,
      "per": 24.3,
      "pbr": 2.65,
      "roe": 11.5,
      "rsi": 42.2,
      "vol": 0.3303,
      "inTop": false,
      "yutai": null
    },
    {
      "code": "2897.T",
      "name": "日清食品HD",
      "price": 2853.5,
      "divPerShare": 70.0,
      "exDivDate": "2026-09-29",
      "dividendYield": 2.42,
      "per": 18.3,
      "pbr": 1.58,
      "roe": 9.2,
      "rsi": 50.5,
      "vol": 0.2622,
      "inTop": false,
      "yutai": null
    },
    {
      "code": "8113.T",
      "name": "ユニ・チャーム",
      "price": 956.7,
      "divPerShare": 22.0,
      "exDivDate": "2026-12-29",
      "dividendYield": 2.29,
      "per": 27.7,
      "pbr": 2.1,
      "roe": 7.7,
      "rsi": 51.6,
      "vol": 0.3199,
      "inTop": false,
      "yutai": null
    },
    {
      "code": "3092.T",
      "name": "ZOZO",
      "price": 1118.0,
      "divPerShare": 40.0,
      "exDivDate": "2026-09-29",
      "dividendYield": 3.52,
      "per": 20.7,
      "pbr": 9.26,
      "roe": 46.6,
      "rsi": 41.9,
      "vol": 0.3137,
      "inTop": false,
      "yutai": null
    },
    {
      "code": "4755.T",
      "name": "楽天グループ",
      "price": 794.4,
      "divPerShare": null,
      "exDivDate": "2022-12-29",
      "dividendYield": null,
      "per": null,
      "pbr": 1.92,
      "roe": -5.2,
      "rsi": 72.7,
      "vol": 0.3499,
      "inTop": false,
      "yutai": null
    },
    {
      "code": "4689.T",
      "name": "LINEヤフー",
      "price": 436.8,
      "divPerShare": 11.0,
      "exDivDate": "2027-03-30",
      "dividendYield": 2.49,
      "per": 15.7,
      "pbr": 1.0,
      "roe": 7.9,
      "rsi": 50.8,
      "vol": 0.3402,
      "inTop": false,
      "yutai": null
    },
    {
      "code": "9843.T",
      "name": "ニトリホールディングス",
      "price": 2385.5,
      "divPerShare": 32.0,
      "exDivDate": "2026-09-29",
      "dividendYield": 1.34,
      "per": 15.1,
      "pbr": 1.36,
      "roe": 9.4,
      "rsi": 53.3,
      "vol": 0.4144,
      "inTop": false,
      "yutai": null
    },
    {
      "code": "8252.T",
      "name": "丸井グループ",
      "price": 2920.0,
      "divPerShare": 134.0,
      "exDivDate": "2026-09-29",
      "dividendYield": 4.53,
      "per": 18.4,
      "pbr": 2.15,
      "roe": 11.7,
      "rsi": 56.3,
      "vol": 0.2209,
      "inTop": false,
      "yutai": null
    },
    {
      "code": "8591.T",
      "name": "オリックス",
      "price": 6623.0,
      "divPerShare": 156.1,
      "exDivDate": "2026-03-30",
      "dividendYield": 2.37,
      "per": 16.6,
      "pbr": 1.62,
      "roe": 10.4,
      "rsi": 62.7,
      "vol": 0.3787,
      "inTop": false,
      "yutai": "2024年に株主優待は廃止済み"
    },
    {
      "code": "2670.T",
      "name": "ABCマート",
      "price": 2634.5,
      "divPerShare": 80.0,
      "exDivDate": "2026-08-28",
      "dividendYield": 3.05,
      "per": 14.1,
      "pbr": 1.63,
      "roe": 12.4,
      "rsi": 41.8,
      "vol": 0.3086,
      "inTop": false,
      "yutai": null
    },
    {
      "code": "4324.T",
      "name": "電通グループ",
      "price": 3339.0,
      "divPerShare": null,
      "exDivDate": "2025-12-29",
      "dividendYield": null,
      "per": null,
      "pbr": 2.08,
      "roe": -47.0,
      "rsi": 65.7,
      "vol": 0.3499,
      "inTop": false,
      "yutai": null
    },
    {
      "code": "2413.T",
      "name": "エムスリー",
      "price": 1816.5,
      "divPerShare": 22.0,
      "exDivDate": "2026-03-30",
      "dividendYield": 1.2,
      "per": 25.1,
      "pbr": 2.97,
      "roe": 12.6,
      "rsi": 45.3,
      "vol": 0.3724,
      "inTop": false,
      "yutai": null
    },
    {
      "code": "3791.T",
      "name": "IGポート",
      "price": 936.0,
      "divPerShare": 13.0,
      "exDivDate": "2027-05-28",
      "dividendYield": 1.31,
      "per": 28.1,
      "pbr": 1.9,
      "roe": 7.5,
      "rsi": 19.2,
      "vol": 0.5161,
      "inTop": false,
      "yutai": null
    },
    {
      "code": "9166.T",
      "name": "GENDA",
      "price": 588.0,
      "divPerShare": 8.0,
      "exDivDate": "2026-07-30",
      "dividendYield": 1.37,
      "per": 27.6,
      "pbr": 1.64,
      "roe": 5.5,
      "rsi": 52.2,
      "vol": 0.6472,
      "inTop": false,
      "yutai": null
    },
    {
      "code": "5599.T",
      "name": "S&J",
      "price": 1115.0,
      "divPerShare": 17.0,
      "exDivDate": "2027-03-30",
      "dividendYield": 1.5,
      "per": 15.3,
      "pbr": 2.88,
      "roe": 19.5,
      "rsi": 60.2,
      "vol": 0.7272,
      "inTop": false,
      "yutai": null
    },
    {
      "code": "4420.T",
      "name": "イーソル",
      "price": 773.0,
      "divPerShare": 5.5,
      "exDivDate": "2026-12-29",
      "dividendYield": 0.72,
      "per": 24.8,
      "pbr": 2.52,
      "roe": 13.1,
      "rsi": 43.8,
      "vol": 0.6215,
      "inTop": false,
      "yutai": null
    },
    {
      "code": "9412.T",
      "name": "スカパーJSAT",
      "price": 2272.0,
      "divPerShare": 48.0,
      "exDivDate": "2026-09-29",
      "dividendYield": 2.09,
      "per": 27.6,
      "pbr": 2.12,
      "roe": 8.0,
      "rsi": 27.0,
      "vol": 0.6384,
      "inTop": false,
      "yutai": null
    },
    {
      "code": "9602.T",
      "name": "東宝",
      "price": 1359.5,
      "divPerShare": 22.0,
      "exDivDate": "2026-08-28",
      "dividendYield": 1.6,
      "per": 22.2,
      "pbr": 2.26,
      "roe": 9.7,
      "rsi": 58.7,
      "vol": 0.3242,
      "inTop": false,
      "yutai": null
    },
    {
      "code": "4816.T",
      "name": "東映アニメーション",
      "price": 2634.0,
      "divPerShare": 44.0,
      "exDivDate": "2027-03-30",
      "dividendYield": 1.65,
      "per": 21.5,
      "pbr": 3.15,
      "roe": 15.5,
      "rsi": 57.6,
      "vol": 0.3719,
      "inTop": false,
      "yutai": null
    },
    {
      "code": "2432.T",
      "name": "ディー・エヌ・エー",
      "price": 2413.5,
      "divPerShare": 66.0,
      "exDivDate": "2026-03-30",
      "dividendYield": 2.72,
      "per": 14.1,
      "pbr": 1.11,
      "roe": 7.5,
      "rsi": 10.8,
      "vol": 0.3319,
      "inTop": false,
      "yutai": null
    },
    {
      "code": "3765.T",
      "name": "ガンホー・オンライン・エンターテイメント",
      "price": 2296.0,
      "divPerShare": 90.0,
      "exDivDate": "2025-12-29",
      "dividendYield": 3.9,
      "per": 89.6,
      "pbr": 1.05,
      "roe": 3.3,
      "rsi": 40.3,
      "vol": 0.2698,
      "inTop": false,
      "yutai": null
    },
    {
      "code": "6460.T",
      "name": "セガサミーホールディングス",
      "price": 2429.0,
      "divPerShare": 55.0,
      "exDivDate": "2026-09-29",
      "dividendYield": 2.24,
      "per": null,
      "pbr": 1.39,
      "roe": -1.6,
      "rsi": 65.9,
      "vol": 0.3575,
      "inTop": false,
      "yutai": null
    },
    {
      "code": "9401.T",
      "name": "TBSホールディングス",
      "price": 6103.0,
      "divPerShare": 100.0,
      "exDivDate": "2026-09-29",
      "dividendYield": 1.61,
      "per": 18.4,
      "pbr": 0.85,
      "roe": 5.1,
      "rsi": 32.2,
      "vol": 0.2966,
      "inTop": false,
      "yutai": null
    },
    {
      "code": "9404.T",
      "name": "日本テレビホールディングス",
      "price": 2805.5,
      "divPerShare": 45.0,
      "exDivDate": "2026-09-29",
      "dividendYield": 1.57,
      "per": 12.4,
      "pbr": 0.7,
      "roe": 6.1,
      "rsi": 40.8,
      "vol": 0.234,
      "inTop": false,
      "yutai": null
    },
    {
      "code": "1928.T",
      "name": "積水ハウス",
      "price": 3510.0,
      "divPerShare": 146.0,
      "exDivDate": "2026-07-30",
      "dividendYield": 4.14,
      "per": 8.8,
      "pbr": 1.05,
      "roe": 12.6,
      "rsi": 63.6,
      "vol": 0.1954,
      "inTop": false,
      "yutai": null
    },
    {
      "code": "1925.T",
      "name": "大和ハウス工業",
      "price": 4553.0,
      "divPerShare": 131.0,
      "exDivDate": "2026-09-29",
      "dividendYield": 2.84,
      "per": 8.0,
      "pbr": 0.97,
      "roe": 12.5,
      "rsi": 60.7,
      "vol": 0.1926,
      "inTop": false,
      "yutai": null
    },
    {
      "code": "6740.T",
      "name": "ジャパンディスプレイ",
      "price": 48.0,
      "divPerShare": null,
      "exDivDate": null,
      "dividendYield": null,
      "per": null,
      "pbr": -40.07,
      "roe": null,
      "rsi": 40.9,
      "vol": 2.1384,
      "inTop": false,
      "yutai": null
    },
    {
      "code": "6963.T",
      "name": "ローム",
      "price": 4908.0,
      "divPerShare": 50.0,
      "exDivDate": "2026-03-30",
      "dividendYield": 1.04,
      "per": null,
      "pbr": 2.5,
      "roe": -19.2,
      "rsi": 45.2,
      "vol": 0.7136,
      "inTop": false,
      "yutai": null
    }
  ],
  "alerts": [
    {
      "type": "info",
      "title": "EDINET大量保有: 新着なし",
      "desc": "直近3日間に大量保有報告書の提出はありませんでした（出典: EDINET）"
    },
    {
      "type": "info",
      "title": "空売り残高: マネーフォワード (3994)",
      "desc": "開示合計7.22%・前回比横ばい（2件・出典JPX 07/22時点）"
    },
    {
      "type": "info",
      "title": "空売り残高: カバー (5253)",
      "desc": "開示合計6.92%・前回比減少中（5件・出典JPX 07/22時点）"
    },
    {
      "type": "warn",
      "title": "空売り残高: JFEホールディングス (5411)",
      "desc": "開示合計4.74%・前回比増加中（3件・出典JPX 07/22時点）"
    },
    {
      "type": "warn",
      "title": "逆張り候補: IGポート",
      "desc": "RSI19.2・週次-29.4%・要リスク管理"
    },
    {
      "type": "warn",
      "title": "入替候補OUT: 任天堂",
      "desc": "スコア下位15% (score=0.339)"
    },
    {
      "type": "warn",
      "title": "入替候補OUT: ファーストリテイリング",
      "desc": "スコア下位15% (score=0.336)"
    },
    {
      "type": "warn",
      "title": "入替候補OUT: 味の素",
      "desc": "スコア下位15% (score=0.335)"
    }
  ],
  "flow": {
    "week": "07/06～07/10",
    "flows": [
      {
        "label": "海外投資家",
        "value": 5172
      },
      {
        "label": "個人",
        "value": -1012
      },
      {
        "label": "信託銀行",
        "value": 2287
      },
      {
        "label": "投資信託",
        "value": -6263
      }
    ],
    "source": "JPX 投資部門別売買状況（東証プライム・週次・金額ベース）"
  },
  "themeTrends": [
    {
      "theme": "その他",
      "mentions": 6,
      "pos": 0,
      "neg": 0,
      "prevMentions": 6
    },
    {
      "theme": "AI",
      "mentions": 3,
      "pos": 0,
      "neg": 0,
      "prevMentions": 3
    },
    {
      "theme": "自動車",
      "mentions": 1,
      "pos": 0,
      "neg": 0,
      "prevMentions": 1
    }
  ]
}